xcelium/fifo.v
`timescale 1ns/1ns
module fifo_sync
    // Parameters section
    #( parameter FIFO_DEPTH = 8,
	   parameter DATA_WIDTH = 32)
    // Ports section   
	(input clk, 
     input rst_n,
     input cs,     // chip select	 
     input wr_en, 
     input rd_en, 
     input [DATA_WIDTH-1:0] data_in, 
     output reg [DATA_WIDTH-1:0] data_out, 
	 output empty,
	 output full); 

  localparam FIFO_DEPTH_LOG = $clog2(FIFO_DEPTH);// 
	
    // Declare a by-dimensional array to store the data
  reg [DATA_WIDTH-1:0] fifo [0:FIFO_DEPTH-1];// depth 8 => [0:7] 32 bit elements
	
	// Wr/Rd pointer have 1 extra bits at MSB
  reg [FIFO_DEPTH_LOG:0] write_pointer;//3:0
  reg [FIFO_DEPTH_LOG:0] read_pointer;//3:0

  //write
    always @(posedge clk or negedge rst_n) 
      begin
      if(!rst_n)//rst =0 system reset happens
		    write_pointer <= 0;
      else if (cs && wr_en && !full) begin
          fifo[write_pointer[FIFO_DEPTH_LOG-1:0]] <= data_in;
	       write_pointer <= write_pointer + 1'b1;
      end
      end
  
	//read
	always @(posedge clk or negedge rst_n) 
      begin
	    if(!rst_n)
		    read_pointer <= 0;
      else if (cs && rd_en && !empty) begin
          	data_out <= fifo[read_pointer[FIFO_DEPTH_LOG-1:0]];
	        read_pointer <= read_pointer + 1'b1;
      end
	end
	
	// Declare the empty/full logic
    assign empty = (read_pointer == write_pointer);
	assign full  = (read_pointer == {~write_pointer[FIFO_DEPTH_LOG], write_pointer[FIFO_DEPTH_LOG-1:0]});

  
  /*
    always @(posedge clk) begin
	    if (cs && wr_en && !full)
	        fifo[write_pointer[FIFO_DEPTH_LOG-1:0]] <= data_in;
	end
	
	always @(posedge clk or negedge rst_n) begin
	    if (!rst_n)
		    data_out <= 0;
		else if (cs && rd_en && !empty)
	        data_out <= fifo[read_pointer[FIFO_DEPTH_LOG-1:0]];
	end
*/
endmodule

xcelium/fifo_tb.v


`timescale 1ns/1ns
module tb_fifo_sync();
	
	// Testbench variables
	parameter FIFO_DEPTH = 8;
	parameter DATA_WIDTH = 32;
    reg clk = 0; 
    reg rst_n;
    reg cs;	 
    reg wr_en;
    reg rd_en;
    reg [DATA_WIDTH-1:0] data_in;
    wire [DATA_WIDTH-1:0] data_out;
	wire empty;
	wire full;
	
    integer i;
	
	// Instantiate the DUT
	fifo_sync 
	    #(.FIFO_DEPTH(FIFO_DEPTH),
          .DATA_WIDTH(DATA_WIDTH))
        dut
  	    (.clk     (clk     ), 
         .rst_n   (rst_n   ),
         .cs      (cs      ),	 
         .wr_en   (wr_en   ), 
         .rd_en   (rd_en   ), 
         .data_in (data_in ), 
         .data_out(data_out), 
	     .empty   (empty   ),
	     .full    (full    ));

  	// Create the clock signal
	always begin #5 clk = ~clk; end
  
    task write_data(input [DATA_WIDTH-1:0] d_in);
	    begin
		    @(posedge clk); // sync to positive edge of clock
			cs = 1; wr_en = 1;
			data_in = d_in;
			$display($time, " write_data data_in = %0d", data_in);
			@(posedge clk);
		    cs = 1; wr_en = 0;
		end
	endtask
	
	task read_data();
	    begin
		    @(posedge clk);  // sync to positive edge of clock
			cs = 1; rd_en = 1;
			@(posedge clk);
			//#1;
		    $display($time, " read_data data_out = %0d", data_out);
		    cs = 1; rd_en = 0;
		end
	endtask
	

	
    // Create stimulus	  
    initial begin
	    #1; 
		rst_n = 0; rd_en = 0; wr_en = 0;
		
        @(posedge clk) 
		rst_n = 1;
		$display($time, "\n SCENARIO 1");
		write_data(1);
		write_data(10);
		write_data(100);
		read_data();
		read_data();
		read_data();
		//read_data();
		
        $display($time, "\n SCENARIO 2");
		for (i=0; i<FIFO_DEPTH; i=i+1) begin
		    write_data(2**i);
			read_data();        
		end

        $display($time, "\n SCENARIO 3");		
		for (i=0; i<=FIFO_DEPTH; i=i+1) begin
		    write_data(2**i);
		end
		
		for (i=0; i<FIFO_DEPTH; i=i+1) begin
			read_data();
		end
		
	    #40 $finish;
	end
  
  initial begin
    $dumpfile("dump.vcd"); $dumpvars;
  end
endmodule

xcelium/dump.vcd
$date
    May 12, 2026  16:59:48
$end
$version
    TOOL:	xmsim(64)	22.09-s003
$end
$timescale
    1 ns
$end

$scope module tb_fifo_sync $end
$var parameter 32 !    FIFO_DEPTH $end
$var parameter 32 "    DATA_WIDTH $end
$var reg       1 #    clk $end
$var reg       1 $    rst_n $end
$var reg       1 %    cs $end
$var reg       1 &    wr_en $end
$var reg       1 '    rd_en $end
$var reg      32 (    data_in [31:0] $end
$var wire     32 )    data_out [31:0] $end
$var wire      1 *    empty  $end
$var wire      1 +    full  $end
$var integer  32 ,    i $end

$scope module dut $end
$var parameter 32 -    FIFO_DEPTH $end
$var parameter 32 .    DATA_WIDTH $end
$var wire      1 /    clk  $end
$var wire      1 0    rst_n  $end
$var wire      1 1    cs  $end
$var wire      1 2    wr_en  $end
$var wire      1 3    rd_en  $end
$var wire     32 4    data_in [31:0] $end
$var reg      32 5    data_out [31:0] $end
$var wire      1 *    empty  $end
$var wire      1 +    full  $end
$var parameter 32 6    FIFO_DEPTH_LOG $end
$var reg      32 7    fifo[0] [31:0] $end
$var reg      32 8    fifo[1] [31:0] $end
$var reg      32 9    fifo[2] [31:0] $end
$var reg      32 :    fifo[3] [31:0] $end
$var reg      32 ;    fifo[4] [31:0] $end
$var reg      32 <    fifo[5] [31:0] $end
$var reg      32 =    fifo[6] [31:0] $end
$var reg      32 >    fifo[7] [31:0] $end
$var reg       4 ?    write_pointer [3:0] $end
$var reg       4 @    read_pointer [3:0] $end
$upscope $end


$scope task write_data $end
$var reg      32 A    d_in [31:0] $end
$upscope $end

$upscope $end

$enddefinitions $end
$dumpvars
b11 6
b100000 .
b1000 -
b100000 "
b1000 !
0#
x$
x%
x&
x'
bx (
bx )
x*
x+
bx ,
0/
x0
x1
x2
x3
bx 4
bx 5
bx 7
bx 8
bx 9
bx :
bx ;
bx <
bx =
bx >
bx ?
bx @
bx A
$end
#1
0$
0'
0&
02
03
00
b0 @
b0 ?
0+
1*
#5
1#
1$
b1 A
10
1/
#10
0#
0/
#15
1#
1%
1&
b1 (
b1 4
12
11
1/
b1 7
b1 ?
0*
#20
0#
0/
#25
1#
0&
b1010 A
02
1/
#30
0#
0/
#35
1#
1&
b1010 (
b1010 4
12
1/
b1010 8
b10 ?
#40
0#
0/
#45
1#
0&
b1100100 A
02
1/
#50
0#
0/
#55
1#
1&
b1100100 (
b1100100 4
12
1/
b1100100 9
b11 ?
#60
0#
0/
#65
1#
0&
02
1/
#70
0#
0/
#75
1#
1'
13
1/
b1 5
b1 @
b1 )
#80
0#
0/
#85
1#
0'
03
1/
#90
0#
0/
#95
1#
1'
13
1/
b1010 5
b10 @
b1010 )
#100
0#
0/
#105
1#
0'
03
1/
#110
0#
0/
#115
1#
1'
13
1/
b1100100 5
b11 @
1*
b1100100 )
#120
0#
0/
#125
1#
0'
b0 ,
b1 A
03
1/
#130
0#
0/
#135
1#
1&
b1 (
b1 4
12
1/
b1 :
b100 ?
0*
#140
0#
0/
#145
1#
0&
02
1/
#150
0#
0/
#155
1#
1'
13
1/
b1 5
b100 @
1*
b1 )
#160
0#
0/
#165
1#
0'
b1 ,
b10 A
03
1/
#170
0#
0/
#175
1#
1&
b10 (
b10 4
12
1/
b10 ;
b101 ?
0*
#180
0#
0/
#185
1#
0&
02
1/
#190
0#
0/
#195
1#
1'
13
1/
b10 5
b101 @
1*
b10 )
#200
0#
0/
#205
1#
0'
b10 ,
b100 A
03
1/
#210
0#
0/
#215
1#
1&
b100 (
b100 4
12
1/
b100 <
b110 ?
0*
#220
0#
0/
#225
1#
0&
02
1/
#230
0#
0/
#235
1#
1'
13
1/
b100 5
b110 @
1*
b100 )
#240
0#
0/
#245
1#
0'
b11 ,
b1000 A
03
1/
#250
0#
0/
#255
1#
1&
b1000 (
b1000 4
12
1/
b1000 =
b111 ?
0*
#260
0#
0/
#265
1#
0&
02
1/
#270
0#
0/
#275
1#
1'
13
1/
b1000 5
b111 @
1*
b1000 )
#280
0#
0/
#285
1#
0'
b100 ,
b10000 A
03
1/
#290
0#
0/
#295
1#
1&
b10000 (
b10000 4
12
1/
b10000 >
b1000 ?
0*
#300
0#
0/
#305
1#
0&
02
1/
#310
0#
0/
#315
1#
1'
13
1/
b10000 5
b1000 @
1*
b10000 )
#320
0#
0/
#325
1#
0'
b101 ,
b100000 A
03
1/
#330
0#
0/
#335
1#
1&
b100000 (
b100000 4
12
1/
b100000 7
b1001 ?
0*
#340
0#
0/
#345
1#
0&
02
1/
#350
0#
0/
#355
1#
1'
13
1/
b100000 5
b1001 @
1*
b100000 )
#360
0#
0/
#365
1#
0'
b110 ,
b1000000 A
03
1/
#370
0#
0/
#375
1#
1&
b1000000 (
b1000000 4
12
1/
b1000000 8
b1010 ?
0*
#380
0#
0/
#385
1#
0&
02
1/
#390
0#
0/
#395
1#
1'
13
1/
b1000000 5
b1010 @
1*
b1000000 )
#400
0#
0/
#405
1#
0'
b111 ,
b10000000 A
03
1/
#410
0#
0/
#415
1#
1&
b10000000 (
b10000000 4
12
1/
b10000000 9
b1011 ?
0*
#420
0#
0/
#425
1#
0&
02
1/
#430
0#
0/
#435
1#
1'
13
1/
b10000000 5
b1011 @
1*
b10000000 )
#440
0#
0/
#445
1#
0'
b1000 ,
b0 ,
b1 A
03
1/
#450
0#
0/
#455
1#
1&
b1 (
b1 4
12
1/
b1100 ?
0*
#460
0#
0/
#465
1#
0&
b1 ,
b10 A
02
1/
#470
0#
0/
#475
1#
1&
b10 (
b10 4
12
1/
b1101 ?
#480
0#
0/
#485
1#
0&
b10 ,
b100 A
02
1/
#490
0#
0/
#495
1#
1&
b100 (
b100 4
12
1/
b1110 ?
#500
0#
0/
#505
1#
0&
b11 ,
b1000 A
02
1/
#510
0#
0/
#515
1#
1&
b1000 (
b1000 4
12
1/
b1111 ?
#520
0#
0/
#525
1#
0&
b100 ,
b10000 A
02
1/
#530
0#
0/
#535
1#
1&
b10000 (
b10000 4
12
1/
b0 ?
#540
0#
0/
#545
1#
0&
b101 ,
b100000 A
02
1/
#550
0#
0/
#555
1#
1&
b100000 (
b100000 4
12
1/
b1 ?
#560
0#
0/
#565
1#
0&
b110 ,
b1000000 A
02
1/
#570
0#
0/
#575
1#
1&
b1000000 (
b1000000 4
12
1/
b10 ?
#580
0#
0/
#585
1#
0&
b111 ,
b10000000 A
02
1/
#590
0#
0/
#595
1#
1&
b10000000 (
b10000000 4
12
1/
b11 ?
1+
#600
0#
0/
#605
1#
0&
b1000 ,
b100000000 A
02
1/
#610
0#
0/
#615
1#
1&
b100000000 (
b100000000 4
12
1/
#620
0#
0/
#625
1#
0&
b1001 ,
b0 ,
02
1/
#630
0#
0/
#635
1#
1'
13
1/
b1 5
b1100 @
0+
b1 )
#640
0#
0/
#645
1#
0'
b1 ,
03
1/
#650
0#
0/
#655
1#
1'
13
1/
b10 5
b1101 @
b10 )
#660
0#
0/
#665
1#
0'
b10 ,
03
1/
#670
0#
0/
#675
1#
1'
13
1/
b100 5
b1110 @
b100 )
#680
0#
0/
#685
1#
0'
b11 ,
03
1/
#690
0#
0/
#695
1#
1'
13
1/
b1000 5
b1111 @
b1000 )
#700
0#
0/
#705
1#
0'
b100 ,
03
1/
#710
0#
0/
#715
1#
1'
13
1/
b10000 5
b0 @
b10000 )
#720
0#
0/
#725
1#
0'
b101 ,
03
1/
#730
0#
0/
#735
1#
1'
13
1/
b100000 5
b1 @
b100000 )
#740
0#
0/
#745
1#
0'
b110 ,
03
1/
#750
0#
0/
#755
1#
1'
13
1/
b1000000 5
b10 @
b1000000 )
#760
0#
0/
#765
1#
0'
b111 ,
03
1/
#770
0#
0/
#775
1#
1'
13
1/
b10000000 5
b11 @
1*
b10000000 )
#780
0#
0/
#785
1#
0'
b1000 ,
03
1/
